ScrapingCode.py
minescrapingcraftcode-0.0.1.dist-info/LICENSE.txt
minescrapingcraftcode-0.0.1.dist-info/METADATA
minescrapingcraftcode-0.0.1.dist-info/WHEEL
minescrapingcraftcode-0.0.1.dist-info/top_level.txt
minescrapingcraftcode-0.0.1.dist-info/RECORD
